{
  "version": "7",
  "dialect": "postgresql",
  "entries": [
    {
      "idx": 0,
      "version": "7",
      "when": 1781971108398,
      "tag": "0000_boring_anita_blake",
      "breakpoints": true
    },
    {
      "idx": 1,
      "version": "7",
      "when": 1782056517578,
      "tag": "0001_shorten_fk_constraint_names",
      "breakpoints": true
    },
    {
      "idx": 2,
      "version": "7",
      "when": 1783086869703,
      "tag": "0002_conscious_boomerang",
      "breakpoints": true
    },
    {
      "idx": 3,
      "version": "7",
      "when": 1783089466055,
      "tag": "0003_yellow_shiver_man",
      "breakpoints": true
    },
    {
      "idx": 4,
      "version": "7",
      "when": 1783091942136,
      "tag": "0004_milky_angel",
      "breakpoints": true
    },
    {
      "idx": 5,
      "version": "7",
      "when": 1783093091581,
      "tag": "0005_sharp_the_santerians",
      "breakpoints": true
    },
    {
      "idx": 6,
      "version": "7",
      "when": 1783144640669,
      "tag": "0006_steep_maverick",
      "breakpoints": true
    },
    {
      "idx": 7,
      "version": "7",
      "when": 1783182780793,
      "tag": "0007_colossal_guardian",
      "breakpoints": true
    },
    {
      "idx": 8,
      "version": "7",
      "when": 1783209290467,
      "tag": "0008_expedition_reviews",
      "breakpoints": true
    },
    {
      "idx": 9,
      "version": "7",
      "when": 1783215475340,
      "tag": "0009_combined_gap_closure",
      "breakpoints": true
    }
  ]
}
